README.rst
setup.py
jrtzcloud_python_sdk_core.egg-info/PKG-INFO
jrtzcloud_python_sdk_core.egg-info/SOURCES.txt
jrtzcloud_python_sdk_core.egg-info/dependency_links.txt
jrtzcloud_python_sdk_core.egg-info/requires.txt
jrtzcloud_python_sdk_core.egg-info/top_level.txt
jrtzcloudsdkcore/__init__.py
jrtzcloudsdkcore/abstract_client.py
jrtzcloudsdkcore/abstract_model.py
jrtzcloudsdkcore/credential.py
jrtzcloudsdkcore/sign.py
jrtzcloudsdkcore/exception/__init__.py
jrtzcloudsdkcore/exception/jrtzcloud_sdk_exception.py
jrtzcloudsdkcore/http/__init__.py
jrtzcloudsdkcore/http/request.py
jrtzcloudsdkcore/profile/__init__.py
jrtzcloudsdkcore/profile/client_profile.py
jrtzcloudsdkcore/profile/http_profile.py