Metadata-Version: 1.1
Name: jrtzcloud-python-sdk-core
Version: 1.0.1
Summary: The core module of JrtzCloud Python SDK.
Home-page: https://github.com/jrtzcloud/jrtzcloud-openapi-python-sdk
Author: Jrtz Cloud
Author-email: pantj@investoday.com.cn
License: Apache License 2.0
Keywords: aliyun,sdk,core
Platform: any
Classifier: Development Status :: 5 - Production/Stable
Classifier: Intended Audience :: Developers
Classifier: License :: OSI Approved :: Apache Software License
Classifier: Programming Language :: Python
Classifier: Programming Language :: Python :: 2.6
Classifier: Programming Language :: Python :: 2.7
Classifier: Programming Language :: Python :: 3
Classifier: Programming Language :: Python :: 3.3
Classifier: Programming Language :: Python :: 3.4
Classifier: Programming Language :: Python :: 3.5
Classifier: Programming Language :: Python :: 3.6
Classifier: Programming Language :: Python :: 3.7
Classifier: Topic :: Software Development
